arbe/__init__.py
arbe/backtester.py
arbe/data_conversion.py
arbe-0.1.0.dist-info/LICENSE
arbe-0.1.0.dist-info/METADATA
arbe-0.1.0.dist-info/WHEEL
arbe-0.1.0.dist-info/RECORD
