Metadata-Version: 2.3
Name: arbe
Version: 0.1.0
Summary: 
Author: Nils P. Kujath
Author-email: 63961429+NilsKujath@users.noreply.github.com
Requires-Python: >=3.11
Classifier: Programming Language :: Python :: 3
Classifier: Programming Language :: Python :: 3.11
Classifier: Programming Language :: Python :: 3.12
Classifier: Programming Language :: Python :: 3.13
Requires-Dist: matplotlib (>=3.10.1,<4.0.0)
Requires-Dist: pandas (>=2.2.3,<3.0.0)
Requires-Dist: scipy (>=1.15.2,<2.0.0)
Requires-Dist: seaborn (>=0.13.2,<0.14.0)
